{
  "title": "Rules and conditions of use - Hotel Kole",
  "description": "Find out all the information about the rules and conditions of stay at Hotel Kole.",
  "icons": "/images/favicon.ico",
  "openGraph": {
    "title": "Rules and conditions of use - Hotel Kole",
    "description": "Find out all the information about the rules and conditions of stay at Hotel Kole.",
    "images": [
      {
        "url": "/images/home/banner.jpg",
        "width": 800,
        "height": 600,
        "alt": "Terms and conditions page banner"
      }
    ],
    "type": "website"
  }
}
